[
    {
        "id": 1001,
        "name": "Ironman",
        "imageName": "Ironman",
        "description": "111110111"
    },
    {
        "id": 1002,
        "name": "Capitant Amercian",
        "imageName": "CapitantAmercian",
        "description": "111110111"
    },
    {
        "id": 1003,
        "name": "Thor",
        "imageName": "Thor",
        "description": "111110111"
    },
    {
        "id": 1004,
        "name": "Black Widow",
        "imageName": "BlackWidow",
        "description": "111110111"
    },
    {
        "id": 1005,
        "name": "Hulk",
        "imageName": "Hulk",
        "description": "111110111"
    },
    {
        "id": 1006,
        "name": "Hawkeye",
        "imageName": "Hawkeye",
        "description": "111110111"
    }
]
